{
    "DialogShowWheel": 0b,
    "AvailabilityQuestId": -1,
    "Options": [
        {
            "OptionSlot": 0,
            "Option": {
                "DialogCommand": "",
                "Dialog": 368,
                "Title": "你觉得这样行得通吗？",
                "DialogColor": 2028317,
                "OptionType": 1
            }
        }
    ],
    "DialogHideNPC": 0b,
    "AvailabilityFactionStance": 0,
    "AvailabilityQuest": 0,
    "AvailabilityDialog4": 0,
    "AvailabilityDialog3": 0,
    "AvailabilityQuest2": 0,
    "AvailabilityQuest3": 0,
    "AvailabilityQuest4": 0,
    "ModRev": 18,
    "DecreaseFaction1Points": 0b,
    "DialogQuest": -1,
    "AvailabilityDialog2": 0,
    "OptionFactions1": -1,
    "AvailabilityDayTime": 0,
    "OptionFactions2": -1,
    "AvailabilityFaction2Id": -1,
    "OptionFaction1Points": 100,
    "DialogDisableEsc": 0b,
    "AvailabilityFaction": 0,
    "DialogTitle": "The Spirit Broken III",
    "AvailabilityDialog": 0,
    "AvailabilityFaction2": 0,
    "AvailabilityFactionId": -1,
    "AvailabilityFaction2Stance": 0,
    "DialogCommand": "",
    "AvailabilityDialogId": -1,
    "OptionFaction2Points": 100,
    "DialogText": "克罗米斯是一位强大的战士，如果他能再次拥有自己的武器，他就会想起那段光 荣的往事。他的武器被夺走，作为礼物送给了哈拉德人首领的爪牙，成为了布里 米加克战胜自由民的信物。这些邪恶爪牙各自占据着哈拉德南部的一个前哨站。",
    "AvailabilityQuest4Id": -1,
    "AvailabilityQuest3Id": -1,
    "AvailabilityQuest2Id": -1,
    "AvailabilityDialog2Id": -1,
    "AvailabilityDialog3Id": -1,
    "AvailabilityDialog4Id": -1,
    "AvailabilityMinPlayerLevel": 0,
    "DecreaseFaction2Points": 0b,
    "DialogMail": {
        "Sender": "",
        "BeenRead": 0b,
        "Message": {
        },
        "MailItems": [
        ],
        "MailQuest": -1,
        "TimePast": 1502380496979L,
        "Time": 0L,
        "Subject": ""
    }
}
